Metadata-Version: 1.1
Name: dockerfile-requirements
Version: 0.0.1
Summary: Inlining requirements.txt files into Dockerfiles for better caching.
Home-page: https://github.com/hchasestevens/dockerfile-requirements
Author: H. Chase Stevens
Author-email: chase@chasestevens.com
License: MIT
Platform: any
Classifier: Programming Language :: Python
Classifier: Programming Language :: Python :: 2
Classifier: Programming Language :: Python :: 2.7
Classifier: Programming Language :: Python :: 3
Classifier: Programming Language :: Python :: 3.6
Classifier: Topic :: Software Development :: Libraries :: Python Modules
Classifier: Intended Audience :: Developers
Classifier: Operating System :: OS Independent
Classifier: License :: OSI Approved :: MIT License
